maildown/__init__.py
maildown/application.py
maildown/backends/__init__.py
maildown/backends/aws.py
maildown/backends/base.py
maildown/commands.py
maildown/my-style.css
maildown/renderer.py
maildown/style.css
maildown/template.jinja2
maildown/test.html
maildown/test.md
maildown/utilities.py
maildown-1.4.0.dist-info/LICENSE
maildown-1.4.0.dist-info/METADATA
maildown-1.4.0.dist-info/WHEEL
maildown-1.4.0.dist-info/entry_points.txt
maildown-1.4.0.dist-info/RECORD
