Metadata-Version: 2.1
Name: maildown
Version: 1.4.0
Summary: A super simple CLI for sending emails
Author: Christopher Davies
Author-email: christopherdavies553@gmail.com
Requires-Python: >=3.12,<4.0
Classifier: Programming Language :: Python :: 3
Classifier: Programming Language :: Python :: 3.12
Classifier: Programming Language :: Python :: 3.13
Requires-Dist: boto3 (>=1.35.50,<2.0.0)
Requires-Dist: cleo (>=2.1.0,<3.0.0)
Requires-Dist: coverage (>=7.6.4,<8.0.0)
Requires-Dist: flake8 (>=7.1.1,<8.0.0)
Requires-Dist: jinja2 (>=3.1.4,<4.0.0)
Requires-Dist: mistune (>=3.0.2,<4.0.0)
Requires-Dist: mock (>=5.1.0,<6.0.0)
Requires-Dist: mypy (>=1.13.0,<2.0.0)
Requires-Dist: premailer (>=3.10.0,<4.0.0)
Requires-Dist: pygments (>=2.18.0,<3.0.0)
Requires-Dist: requests (>=2.32.3,<3.0.0)
Requires-Dist: toml (>=0.10.2,<0.11.0)
